{
 "random_seed": 2818494190, 
 "PARAMETERS": {
  "RADIUS1": 908879.259, 
  "QUADS": 3, 
  "RADIUS2": 439278.431, 
  "DIST": 686466.411, 
  "F_PTS": 26, 
  "K_PTS": 27, 
  "EPSILON": 1.714, 
  "LENGTH1": 462459.764, 
  "G_PTS": 30, 
  "Q_PTS": 21, 
  "N_PTS": 49, 
  "C_PTS": 20, 
  "AREA2": 547674.539, 
  "LENGTH2": 576781.275, 
  "B_PTS": 25, 
  "D_PTS": 24, 
  "AREA1": 652315.436, 
  "A_PTS": 3, 
  "E_PTS": 19
 }, 
 "NUMPOINTS": 56, 
 "points": [
  [
   -951861.507, 
   -696397.903
  ], 
  [
   -640370.185, 
   636154.125
  ], 
  [
   242807.966, 
   956411.356
  ], 
  [
   311255.748, 
   -342257.001
  ], 
  [
   -373235.47, 
   447093.539
  ], 
  [
   -59.694, 
   323360.299
  ], 
  [
   -763765.982, 
   -423777.103
  ], 
  [
   -380376.864, 
   -520574.042
  ], 
  [
   426656.603, 
   -18681.96
  ], 
  [
   618360.027, 
   -192703.682
  ], 
  [
   -218382.218, 
   -324053.233
  ], 
  [
   260102.142, 
   853296.693
  ], 
  [
   -919257.588, 
   21506.947
  ], 
  [
   -462485.5, 
   593417.769
  ], 
  [
   174410.678, 
   313084.355
  ], 
  [
   -630147.509, 
   668911.511
  ], 
  [
   146709.735, 
   66842.866
  ], 
  [
   242457.057, 
   416914.519
  ], 
  [
   896040.287, 
   47190.983
  ], 
  [
   -901401.207, 
   -351256.185
  ], 
  [
   -300990.153, 
   -931388.735
  ], 
  [
   631461.783, 
   182588.836
  ], 
  [
   7762.81, 
   884795.265
  ], 
  [
   605606.392, 
   955036.737
  ], 
  [
   585455.017, 
   -668154.889
  ], 
  [
   -603272.729, 
   222081.818
  ], 
  [
   -400080.6, 
   -21563.961
  ], 
  [
   159199.128, 
   -4008.174
  ], 
  [
   -564481.41, 
   545148.548
  ], 
  [
   -653912.352, 
   -136901.615
  ], 
  [
   -567723.116, 
   617252.943
  ], 
  [
   -831307.279, 
   33517.242
  ], 
  [
   -532547.897, 
   147952.425
  ], 
  [
   -722698.072, 
   538364.271
  ], 
  [
   390774.954, 
   711664.691
  ], 
  [
   672501.57, 
   -674447.523
  ], 
  [
   889966.116, 
   -857814.471
  ], 
  [
   -547847.733, 
   641336.039
  ], 
  [
   -970325.201, 
   -953430.765
  ], 
  [
   -835244.376, 
   -61278.712
  ], 
  [
   -619095.849, 
   -799917.035
  ], 
  [
   -65847.076, 
   506997.008
  ], 
  [
   624253.839, 
   363036.957
  ], 
  [
   -542406.051, 
   575023.559
  ], 
  [
   100776.117, 
   -341990.613
  ], 
  [
   622652.821, 
   -643677.788
  ], 
  [
   -877159.314, 
   988642.901
  ], 
  [
   278177.082, 
   163073.838
  ], 
  [
   428965.992, 
   -921837.334
  ], 
  [
   548482.509, 
   -985887.983
  ], 
  [
   -939283.354, 
   44255.735
  ], 
  [
   27043.283, 
   101907.553
  ], 
  [
   704416.432, 
   532363.655
  ], 
  [
   824226.689, 
   -237102.638
  ], 
  [
   242527.961, 
   -297942.873
  ], 
  [
   610144.698, 
   156995.881
  ]
 ], 
 "PUV": [
  true, 
  true, 
  true, 
  true, 
  false, 
  false, 
  true, 
  false, 
  false, 
  false, 
  false, 
  true, 
  false, 
  true, 
  true
 ], 
 "LCM": {
  "11": [
   "NOTUSED", 
   "ORR", 
   "NOTUSED", 
   "NOTUSED", 
   "NOTUSED", 
   "ORR", 
   "ORR", 
   "ORR", 
   "NOTUSED", 
   "NOTUSED", 
   "ORR", 
   "ORR", 
   "ORR", 
   "ORR", 
   "NOTUSED"
  ], 
  "10": [
   "NOTUSED", 
   "NOTUSED", 
   "ANDD", 
   "ORR", 
   "ANDD", 
   "NOTUSED", 
   "NOTUSED", 
   "ORR", 
   "ANDD", 
   "ORR", 
   "NOTUSED", 
   "ORR", 
   "ORR", 
   "NOTUSED", 
   "NOTUSED"
  ], 
  "13": [
   "ANDD", 
   "ANDD", 
   "ORR", 
   "ANDD", 
   "ORR", 
   "NOTUSED", 
   "ORR", 
   "ANDD", 
   "NOTUSED", 
   "NOTUSED", 
   "NOTUSED", 
   "ORR", 
   "ANDD", 
   "ORR", 
   "ANDD"
  ], 
  "12": [
   "ANDD", 
   "NOTUSED", 
   "ANDD", 
   "ANDD", 
   "ANDD", 
   "NOTUSED", 
   "ORR", 
   "ORR", 
   "ANDD", 
   "ORR", 
   "ORR", 
   "ORR", 
   "ANDD", 
   "ANDD", 
   "ORR"
  ], 
  "14": [
   "ANDD", 
   "NOTUSED", 
   "ORR", 
   "ORR", 
   "ORR", 
   "NOTUSED", 
   "ORR", 
   "ORR", 
   "ANDD", 
   "NOTUSED", 
   "NOTUSED", 
   "NOTUSED", 
   "ORR", 
   "ANDD", 
   "ORR"
  ], 
  "1": [
   "NOTUSED", 
   "ORR", 
   "NOTUSED", 
   "ANDD", 
   "ORR", 
   "ORR", 
   "ANDD", 
   "ANDD", 
   "ORR", 
   "ANDD", 
   "NOTUSED", 
   "ORR", 
   "NOTUSED", 
   "ANDD", 
   "NOTUSED"
  ], 
  "0": [
   "ORR", 
   "NOTUSED", 
   "NOTUSED", 
   "NOTUSED", 
   "ANDD", 
   "NOTUSED", 
   "NOTUSED", 
   "ORR", 
   "ORR", 
   "NOTUSED", 
   "NOTUSED", 
   "NOTUSED", 
   "ANDD", 
   "ANDD", 
   "ANDD"
  ], 
  "3": [
   "NOTUSED", 
   "ANDD", 
   "ORR", 
   "ANDD", 
   "ANDD", 
   "ANDD", 
   "ANDD", 
   "ORR", 
   "ANDD", 
   "NOTUSED", 
   "ORR", 
   "NOTUSED", 
   "ANDD", 
   "ANDD", 
   "ORR"
  ], 
  "2": [
   "NOTUSED", 
   "NOTUSED", 
   "ORR", 
   "ORR", 
   "ORR", 
   "ANDD", 
   "ORR", 
   "ANDD", 
   "ORR", 
   "NOTUSED", 
   "ANDD", 
   "NOTUSED", 
   "ANDD", 
   "ORR", 
   "ORR"
  ], 
  "5": [
   "NOTUSED", 
   "ORR", 
   "ANDD", 
   "ANDD", 
   "ORR", 
   "NOTUSED", 
   "NOTUSED", 
   "ANDD", 
   "ORR", 
   "ORR", 
   "NOTUSED", 
   "ORR", 
   "NOTUSED", 
   "NOTUSED", 
   "NOTUSED"
  ], 
  "4": [
   "ANDD", 
   "ORR", 
   "ORR", 
   "ANDD", 
   "NOTUSED", 
   "ORR", 
   "ORR", 
   "NOTUSED", 
   "NOTUSED", 
   "NOTUSED", 
   "ANDD", 
   "NOTUSED", 
   "ANDD", 
   "ORR", 
   "ORR"
  ], 
  "7": [
   "ORR", 
   "ANDD", 
   "ANDD", 
   "ORR", 
   "NOTUSED", 
   "ANDD", 
   "ORR", 
   "ANDD", 
   "ANDD", 
   "NOTUSED", 
   "ORR", 
   "ORR", 
   "ORR", 
   "ANDD", 
   "ORR"
  ], 
  "6": [
   "NOTUSED", 
   "ANDD", 
   "ORR", 
   "ANDD", 
   "ORR", 
   "NOTUSED", 
   "NOTUSED", 
   "ORR", 
   "NOTUSED", 
   "NOTUSED", 
   "NOTUSED", 
   "ORR", 
   "ORR", 
   "ORR", 
   "ORR"
  ], 
  "9": [
   "NOTUSED", 
   "ANDD", 
   "NOTUSED", 
   "NOTUSED", 
   "NOTUSED", 
   "ORR", 
   "NOTUSED", 
   "NOTUSED", 
   "ORR", 
   "ORR", 
   "ORR", 
   "NOTUSED", 
   "ORR", 
   "NOTUSED", 
   "NOTUSED"
  ], 
  "8": [
   "ORR", 
   "ORR", 
   "ORR", 
   "ANDD", 
   "NOTUSED", 
   "ORR", 
   "NOTUSED", 
   "ANDD", 
   "ORR", 
   "ORR", 
   "ANDD", 
   "NOTUSED", 
   "ANDD", 
   "NOTUSED", 
   "ANDD"
  ]
 }
}